Workbook
Name Currency: 'Funding Goal'!$D$7

Sheet Funding Goal
A1: Project Budget Template, Design & Technology | G1: PHASE LEGEND
A2: Add at least three expected totals to the green table below. We’ve provided optional tabs of recommended categories to help you itemize your budget. | G2: Funding | H2: Pitching and gathering support for your campaign
A3: Delete or add green rows to the table below as needed. These feed directly in a budget graphic that we’ll generate in the Funding section of your project editor. | G3: Making | H3: Manufacturing your product, finalizing your app, printing your book, etc.
A4: Use this template to build an informed budget and set a funding goal. We’re able to see this document—which helps us better understand how creators like you prepare for your campaign and project—but will never share it without your explicit permission. | G4: Fulfilling | H4: Delivering rewards to backers
A5: =HYPERLINK("https://iter.ly/yl0jq","Answer a few quick questions about this spreadsheet. ") -> Answer a few quick questions about this spreadsheet. | G5: Multiple/Other | H5: Work spanning multiple phases, e.g., paying yourself
A7: COST CATEGORY | B7: DESCRIPTION (OPTIONAL) | C7: PHASE | D7: CA$ | E7: EXPECTED TOTAL
A8: Research & Development | C8: Making | D8: =$D$7 -> CA$ | E8: 0
A9: Manufacturing | C9: Making | D9: =$D$7 -> CA$ | E9: 0
A10: Packaging & Shipping | C10: Fulfilling | D10: =$D$7 -> CA$ | E10: 0
A11: Labor | C11: Multiple/Other | D11: =$D$7 -> CA$ | E11: 0
A12: Subtotal | D12: =$D$7 -> CA$ | E12: =sum(E8:E11) -> 0
C13: PERCENTAGE
A14: Kickstarter fee | B14: We collect a flat 5% fee from every successful campaign. | C14: 0.05 | D14: =$D$7 -> CA$ | E14: =E19*C14 -> 0
A15: Payment processing fee | B15: This average varies based on your project's location and total number of backers. | C15: 0.05 | D15: =$D$7 -> CA$ | E15: =E19*C15 -> 0
A16: Taxes | B16: Set aside a perecentage for taxes—see a professional adviser for additional guidance. | C16: 0 | D16: =$D$7 -> CA$ | E16: =C16*(E19-sum(E14:E15)) -> 0
A17: Margin of error | B17: Include a buffer to cover any miscalculations. | C17: 0.1 | D17: =$D$7 -> CA$ | E17: =C17*E12 -> 0
A19: Estimated funding goal | D19: =$D$7 -> CA$ | E19: =CEILING(((C17+1)*E12)/(0.9-0.9*C16),100) -> 0

Sheet R&D
A1: Research & Development
A2: Research costs often have no outcome, but can bring new knowledge to the ongoing development and improvements around your project. This includes quality checks, market opportunity, and production timeline.
A3: Estimate and track these peripheral expenses below with as much detail as possible.
A4: Add your expected total to the Research & Development cost category row in the Funding Goal tab.
A6: ITEM | B6: DESCRIPTION | C6: DATE | D6: LEAD TIME | F6: EXPECTED TOTAL
A7: Cost 1 | E7: ='Funding Goal'!$D$7 -> CA$ | F7: 0
A8: Cost 2 | E8: ='Funding Goal'!$D$7 -> CA$ | F8: 0
A9: Cost 3 | E9: ='Funding Goal'!$D$7 -> CA$ | F9: 0
F11: TOTAL
E12: ='Funding Goal'!$D$7 -> CA$ | F12: =SUM(F7:F10) -> 0

Sheet Manufacturing
A1: Manufacturing
A2: Consider your expected costs, quantities, and lead times to produce and review prototypes and final versions of your project.
A3: Adjust your cost per unit based on the order size if necessary.
A4: Add your expected total to the Manufacturing Units cost category row in the Funding Goal tab.
A6: SMALL ORDER (100 UNITS)
A8: ITEM | B8: DESCRIPTION | C8: EXPECTED COST / UNIT | D8: UNITS | E8: LEAD TIME | G8: EXPECTED TOTAL
A9: Part 1 | C9: 0 | D9: 0 | E9: 0 weeks | F9: ='Funding Goal'!$D$7 -> CA$ | G9: =0 -> 0
A10: Part 2 | C10: 0 | D10: 0 | E10: 0 weeks | F10: ='Funding Goal'!$D$7 -> CA$ | G10: 0
A11: Part 3 | C11: 0 | D11: 0 | E11: 0 weeks | F11: ='Funding Goal'!$D$7 -> CA$ | G11: 0
G13: SMALL ORDER TOTAL
F14: ='Funding Goal'!$D$7 -> CA$ | G14: =SUM(G9:G13) -> 0
A16: MEDIUM ORDER (500 UNITS)
A18: ITEM | B18: DESCRIPTION | C18: EXPECTED COST / UNIT | D18: UNITS | E18: LEAD TIME | G18: EXPECTED TOTAL
A19: Part 1 | C19: 0 | D19: 0 | E19: 0 weeks | F19: ='Funding Goal'!$D$7 -> CA$ | G19: =C19*D19 -> 0
A20: Part 2 | C20: 0 | D20: 0 | E20: 0 weeks | F20: ='Funding Goal'!$D$7 -> CA$ | G20: =C20*D20 -> 0
A21: Part 3 | C21: 0 | D21: 0 | E21: 0 weeks | F21: ='Funding Goal'!$D$7 -> CA$ | G21: =C21*D21 -> 0
G23: MEDIUM ORDER TOTAL
F24: ='Funding Goal'!$D$7 -> CA$ | G24: =SUM(G19:G23) -> 0

Sheet Packaging
A1: Packaging
A2: You should shop around for packaging options from as many vendors as you can. Include hard costs such as structural and graphic design, custom manufacturing, and supplies.
A3: The fragility of the items you’ll ship are important to your packaging decisions. How will you securely send your items so that they aren’t damaged during travel?
A4: Add your expected total to the Packaging cost category row in the Funding Goal tab.
A6: ITEM | B6: DESCRIPTION | C6: QUANTITY | D6: EXPECTED COST | E6: LEAD TIME | G6: EXPECTED TOTAL
A7: Item 1 | C7: 0 | D7: 0 | F7: ='Funding Goal'!$D$7 -> CA$ | G7: =C7*D7 -> 0
A8: Item 2 | C8: 0 | D8: 0 | F8: ='Funding Goal'!$D$7 -> CA$ | G8: =C8*D8 -> 0
A9: Item 3 | C9: 0 | D9: 0 | F9: ='Funding Goal'!$D$7 -> CA$ | G9: =C9*D9 -> 0
A10: Item 4 | C10: 0 | D10: 0 | F10: ='Funding Goal'!$D$7 -> CA$ | G10: =C10*D10 -> 0
G12: TOTAL
F13: ='Funding Goal'!$D$7 -> CA$ | G13: =SUM(G7:G12) -> 0

Sheet Shipping
A1: Shipping
A2: First, establish your individual reward tiers and decide where in the world you’ll offer to ship them. Then estimate the size and weight of your complete packaging for each tier item so you can calculate a shipping quote. Use your best judgement to estimate how many backers each tier might attract, especially if you’re offering an unlimited amount of a reward.
A3: International shipping can be complex and expensive—explore packaging options and shipping estimates thoroughly before making a final decision about where you will ship your rewards.
A4: Add your expected total to the Shipping cost category row in the Funding Goal tab.
A6: REWARD | B6: EXPECTED BACKERS | C6: SHIPPING COST | E6: EXPECTED TOTAL
A7: Tier 1 (U.S.) | B7: 0 | C7: 0 | D7: ='Funding Goal'!$D$7 -> CA$ | E7: =B7*C7 -> 0
A8: Tier 1 (UK) | B8: 0 | C8: 0 | D8: ='Funding Goal'!$D$7 -> CA$ | E8: =B8*C8 -> 0
A9: Tier 1 (India) | B9: 0 | C9: 0 | D9: ='Funding Goal'!$D$7 -> CA$ | E9: =B9*C9 -> 0
A10: Tier 2 (U.S.) | B10: 0 | C10: 0 | D10: ='Funding Goal'!$D$7 -> CA$ | E10: =B10*C10 -> 0
A11: Tier 2 (UK) | B11: 0 | C11: 0 | D11: ='Funding Goal'!$D$7 -> CA$ | E11: =B11*C11 -> 0
A12: Tier 3 (India) | B12: 0 | C12: 0 | D12: ='Funding Goal'!$D$7 -> CA$ | E12: =C12 -> 0
E14: TOTAL
D15: ='Funding Goal'!$D$7 -> CA$ | E15: =SUM(E7:E12) -> 0

Sheet Labor
A1: Labor
A2: It’s crucial that you pay yourself for the time you invest in bringing your project to life. Be honest about your tasks and how long it will take you to complete them. Do the same for any assistants or collaborators that will also be an active part of this process.
A3: Add your expected total to the Labor cost category row in the Funding Goal tab.
A5: Labor | B5: HOURS | C5: RATE | E5: EXPECTED TOTAL
A6: Your labor cost | B6: 0 | C6: 0 | D6: ='Funding Goal'!$D$7 -> CA$ | E6: =B6*C6 -> 0
A7: Assistant | B7: 0 | C7: 0 | D7: ='Funding Goal'!$D$7 -> CA$ | E7: =B7*C7 -> 0
E9: TOTAL
D10: ='Funding Goal'!$D$7 -> CA$ | E10: =SUM(E6:E7) -> 0

Sheet Miscellaneous
A1: Miscellaneous
A2: Use this final tab to track costs that don’t fit into any of the other categories.
A3: Add your expected total to the Labor cost category row in the Funding Goal tab.
A5: ITEM | B5: DESCRIPTION | C5: DATE | D5: LEAD TIME | F5: EXPECTED TOTAL
A6: Misc Cost 1 | E6: ='Funding Goal'!$D$7 -> CA$ | F6: 0
A7: Misc Cost 2 | E7: ='Funding Goal'!$D$7 -> CA$ | F7: 0
A8: Misc Cost 3 | E8: ='Funding Goal'!$D$7 -> CA$ | F8: 0
F10: TOTAL
E11: ='Funding Goal'!$D$7 -> CA$ | F11: =SUM(F6:F9) -> 0
